urbansim_defaults/__init__.py
urbansim_defaults/datasources.py
urbansim_defaults/models.py
urbansim_defaults/utils.py
urbansim_defaults/variables.py
urbansim_defaults-0.2.dist-info/METADATA
urbansim_defaults-0.2.dist-info/RECORD
urbansim_defaults-0.2.dist-info/WHEEL
urbansim_defaults-0.2.dist-info/top_level.txt
